bootstrap25/__init__.py
bootstrap25/ALL_PRACT_EASY/P1.py
bootstrap25/ALL_PRACT_EASY/P10.py
bootstrap25/ALL_PRACT_EASY/P11.py
bootstrap25/ALL_PRACT_EASY/P12.py
bootstrap25/ALL_PRACT_EASY/P2.py
bootstrap25/ALL_PRACT_EASY/P3.py
bootstrap25/ALL_PRACT_EASY/P4.py
bootstrap25/ALL_PRACT_EASY/P5.py
bootstrap25/ALL_PRACT_EASY/P7.py
bootstrap25/ALL_PRACT_EASY/P8.py
bootstrap25/ALL_PRACT_EASY/P9.py
bootstrap25/ALL_PRACT_EASY/p6.py
bootstrap25/ALL_PRACT_PROPER/PRACTICAL_NO_01_new[1].pdf
bootstrap25/ALL_PRACT_PROPER/PRACTICAL_NO_02_new[1].pdf
bootstrap25/ALL_PRACT_PROPER/PRACTICAL_NO_03_-_new[1].pdf
bootstrap25/ALL_PRACT_PROPER/PRACTICAL_NO_04_-_new[1].pdf
bootstrap25/ALL_PRACT_PROPER/PRACTICAL_NO_05_new[1].pdf
bootstrap25/ALL_PRACT_PROPER/PRACTICAL_NO_06_new[1].pdf
bootstrap25/ALL_PRACT_PROPER/PRACTICAL_NO_07_new[1].pdf
bootstrap25/ALL_PRACT_PROPER/PRACTICAL_NO_08[2].pdf
bootstrap25/ALL_PRACT_PROPER/PRACTICAL_NO_09[2].pdf
bootstrap25/ALL_PRACT_PROPER/PRACTICAL_NO_10[1].pdf
bootstrap25/IMPORTANT/AJAX PROGRESS CONTROL AND TREE VIEW CONTROL EXAMPLE/ASPX1.pdf
bootstrap25/IMPORTANT/AJAX PROGRESS CONTROL AND TREE VIEW CONTROL EXAMPLE/ASPX2.pdf
bootstrap25/IMPORTANT/AJAX PROGRESS CONTROL AND TREE VIEW CONTROL EXAMPLE/CS1.pdf
bootstrap25/IMPORTANT/AJAX PROGRESS CONTROL AND TREE VIEW CONTROL EXAMPLE/CS2.pdf
bootstrap25/IMPORTANT/AJAX PROGRESS CONTROL AND TREE VIEW CONTROL EXAMPLE/SITEMAP2.pdf
bootstrap25/IMPORTANT/CONSOLE OPERATION AND CALENDOR CONTROL/ASPX.pdf
bootstrap25/IMPORTANT/CONSOLE OPERATION AND CALENDOR CONTROL/CONSOLE.pdf
bootstrap25/IMPORTANT/CONSOLE OPERATION AND CALENDOR CONTROL/CS.pdf
bootstrap25/IMPORTANT/DATE OPERATION AND STUDENT DETAILS SHOW USING GRIDVIEW/ASPX.pdf
bootstrap25/IMPORTANT/DATE OPERATION AND STUDENT DETAILS SHOW USING GRIDVIEW/ASPX2.pdf
bootstrap25/IMPORTANT/DATE OPERATION AND STUDENT DETAILS SHOW USING GRIDVIEW/CS.pdf
bootstrap25/IMPORTANT/DATE OPERATION AND STUDENT DETAILS SHOW USING GRIDVIEW/CS2.pdf
bootstrap25-0.1.0.dist-info/LICENSE
bootstrap25-0.1.0.dist-info/METADATA
bootstrap25-0.1.0.dist-info/WHEEL
bootstrap25-0.1.0.dist-info/top_level.txt
bootstrap25-0.1.0.dist-info/RECORD
